psmpa_fungi/__init__.py
psmpa_fungi/default.py
psmpa_fungi/psmpa_fungi.py
psmpa_fungi/test.py
psmpa_fungi/util.py
psmpa_fungi/default_files/psmpa_fungi/psmpa_fungi_database_default.tsv.gz
psmpa_fungi/default_files/psmpa_fungi/blast_db/ref18S.ndb
psmpa_fungi/default_files/psmpa_fungi/blast_db/ref18S.nhr
psmpa_fungi/default_files/psmpa_fungi/blast_db/ref18S.nin
psmpa_fungi/default_files/psmpa_fungi/blast_db/ref18S.not
psmpa_fungi/default_files/psmpa_fungi/blast_db/ref18S.nsq
psmpa_fungi/default_files/psmpa_fungi/blast_db/ref18S.ntf
psmpa_fungi/default_files/psmpa_fungi/blast_db/ref18S.nto
psmpa_fungi-0.1.6.data/scripts/psmpa-fungi
psmpa_fungi-0.1.6.dist-info/LICENSE
psmpa_fungi-0.1.6.dist-info/METADATA
psmpa_fungi-0.1.6.dist-info/WHEEL
psmpa_fungi-0.1.6.dist-info/top_level.txt
psmpa_fungi-0.1.6.dist-info/RECORD
